wechatbot/__init__.py
wechatbot/wechat_bot.py
PyWeChatBot-0.0.8.dist-info/LICENSE
PyWeChatBot-0.0.8.dist-info/METADATA
PyWeChatBot-0.0.8.dist-info/WHEEL
PyWeChatBot-0.0.8.dist-info/top_level.txt
PyWeChatBot-0.0.8.dist-info/RECORD
