Metadata-Version: 2.1
Name: PyWeChatBot
Version: 0.0.8
Summary: WeChatBot Send Message
Home-page: https://github.com/xuranyang/PyWeChatBot
Author: xuranyang
Author-email: xuranyang96@gmail.com
License: MIT
Keywords: wechat,bot,wechatbot,wechat bot
Platform: UNKNOWN
Classifier: Operating System :: OS Independent
Classifier: Intended Audience :: Developers
Classifier: License :: OSI Approved :: MIT License
Classifier: Programming Language :: Python :: 3
Requires-Python: >=3.7
Requires-Dist: requests
